qanalytics/Core.py
qanalytics/Enum.py
qanalytics/Request.py
qanalytics/Struct.py
qanalytics/__init__.py
qanalytics/bin/jsoncpp.dll
qanalytics/bin/libcurl-d.dll
qanalytics/bin/libcurl.dll
qanalytics/bin/libjsoncpp.dll
qanalytics/bin/libmariadb.dll
qanalytics/bin/libqAPI.dll
qanalytics/bin/qAPI.dll
qanalytics_win64-0.5.7.dist-info/LICENCE
qanalytics_win64-0.5.7.dist-info/METADATA
qanalytics_win64-0.5.7.dist-info/WHEEL
qanalytics_win64-0.5.7.dist-info/top_level.txt
qanalytics_win64-0.5.7.dist-info/RECORD
