Metadata-Version: 2.1
Name: qanalytics-win64
Version: 0.5.7
Summary: Design and manage your financial derivatives
Author-email: mattcharr <matthieu.charrier.pro@gmail.com>
Maintainer-email: mattcharr <matthieu.charrier.pro@gmail.com>
Project-URL: Homepage, https://github.com/matt-charr/qAPP/
Project-URL: Documentation, https://matt-charr.github.io/qAPP/
Project-URL: Repository, https://github.com/matt-charr/qAPP/
Project-URL: Issues, https://github.com/matt-charr/qAPP/issues/
Project-URL: Changelog, https://github.com/matt-charr/qAPP/releases/
Keywords: finance,pricing,pricer,quantitative,quant,option,structured product,derivatives,model,quantitative
Classifier: Programming Language :: C++
Classifier: Programming Language :: C
Classifier: Programming Language :: Python :: 3.5
Classifier: Topic :: Scientific/Engineering :: Mathematics
Classifier: Topic :: Software Development
Classifier: Topic :: Software Development :: Libraries
Classifier: Operating System :: Microsoft :: Windows
Requires-Python: >=3.5
License-File: LICENCE
